cioseq/LICENSE
cioseq/README.md
cioseq/VERSION
cioseq/__init__.py
cioseq/sequence.py
cioseq-0.5.2.dist-info/licenses/LICENSE
tests/__init__.py
tests/test_sequence.py
cioseq-0.5.2.dist-info/METADATA
cioseq-0.5.2.dist-info/WHEEL
cioseq-0.5.2.dist-info/top_level.txt
cioseq-0.5.2.dist-info/RECORD
