Metadata-Version: 2.4
Name: cioseq
Version: 0.5.2
Summary: Manage sequences of frame numbers.
Home-page: https://github.com/ConductorTechnologies/cioseq
Author: conductor
Author-email: info@conductortech.com
Classifier: Operating System :: OS Independent
Classifier: Programming Language :: Python
Classifier: Topic :: Multimedia :: Graphics :: 3D Rendering
License-File: LICENSE
Requires-Dist: future>=0.18.2
Dynamic: author
Dynamic: author-email
Dynamic: classifier
Dynamic: description
Dynamic: description-content-type
Dynamic: home-page
Dynamic: license-file
Dynamic: requires-dist
Dynamic: summary
